odoo/addons/product_tags_code/README.rst
odoo/addons/product_tags_code/__init__.py
odoo/addons/product_tags_code/__manifest__.py
odoo/addons/product_tags_code/i18n/es.po
odoo/addons/product_tags_code/i18n/it.po
odoo/addons/product_tags_code/i18n/product_tags_code.pot
odoo/addons/product_tags_code/models/__init__.py
odoo/addons/product_tags_code/models/product_tag.py
odoo/addons/product_tags_code/readme/CONFIGURE.md
odoo/addons/product_tags_code/readme/CONTRIBUTORS.md
odoo/addons/product_tags_code/readme/CREDITS.md
odoo/addons/product_tags_code/readme/DESCRIPTION.md
odoo/addons/product_tags_code/static/description/icon.png
odoo/addons/product_tags_code/static/description/index.html
odoo/addons/product_tags_code/tests/__init__.py
odoo/addons/product_tags_code/tests/test_product_tags_code.py
odoo/addons/product_tags_code/views/product_tag_views.xml
odoo_addon_product_tags_code-18.0.1.0.0.2.dist-info/METADATA
odoo_addon_product_tags_code-18.0.1.0.0.2.dist-info/WHEEL
odoo_addon_product_tags_code-18.0.1.0.0.2.dist-info/top_level.txt
odoo_addon_product_tags_code-18.0.1.0.0.2.dist-info/RECORD
